setup.py
hello/__init__.py
hello/hello.py
hello_pip.egg-info/PKG-INFO
hello_pip.egg-info/SOURCES.txt
hello_pip.egg-info/dependency_links.txt
hello_pip.egg-info/not-zip-safe
hello_pip.egg-info/top_level.txt